<?xml version="1.0" encoding="utf-8" ?>
<dwsync>
<file name="font-awesome.css" server="192.168.1.2//var/www/html/dpluso/" local="131297458764026880" remote="131297668200000000" Dst="1" />
<file name="font-awesome.scss" server="192.168.1.2//var/www/html/dpluso/" local="131297458763936826" remote="131297668200000000" Dst="1" />
<file name="_animated.scss" server="192.168.1.2//var/www/html/dpluso/" local="131297458762996257" remote="131297668200000000" Dst="1" />
<file name="_bordered-pulled.scss" server="192.168.1.2//var/www/html/dpluso/" local="131297458763076304" remote="131297668200000000" Dst="1" />
<file name="_core.scss" server="192.168.1.2//var/www/html/dpluso/" local="131297458763136344" remote="131297668200000000" Dst="1" />
<file name="_fixed-width.scss" server="192.168.1.2//var/www/html/dpluso/" local="131297458763186380" remote="131297668200000000" Dst="1" />
<file name="_icons.scss" server="192.168.1.2//var/www/html/dpluso/" local="131297458763406527" remote="131297668200000000" Dst="1" />
<file name="_larger.scss" server="192.168.1.2//var/www/html/dpluso/" local="131297458763346487" remote="131297668200000000" Dst="1" />
<file name="_list.scss" server="192.168.1.2//var/www/html/dpluso/" local="131297458763296454" remote="131297668200000000" Dst="1" />
<file name="_mixins.scss" server="192.168.1.2//var/www/html/dpluso/" local="131297458763496594" remote="131297668200000000" Dst="1" />
<file name="_path.scss" server="192.168.1.2//var/www/html/dpluso/" local="131297458763551643" remote="131297668200000000" Dst="1" />
<file name="_rotated-flipped.scss" server="192.168.1.2//var/www/html/dpluso/" local="131297458763606677" remote="131297668200000000" Dst="1" />
<file name="_screen-reader.scss" server="192.168.1.2//var/www/html/dpluso/" local="131297458763706669" remote="131297668200000000" Dst="1" />
<file name="_stacked.scss" server="192.168.1.2//var/www/html/dpluso/" local="131297458763756703" remote="131297668200000000" Dst="1" />
<file name="_variables.scss" server="192.168.1.2//var/www/html/dpluso/" local="131297458763846760" remote="131297668200000000" Dst="1" />
</dwsync>