<?xml version="1.0" encoding="utf-8" ?>
<dwsync>
<file name="animated-overlay.gif" server="192.168.1.2//var/www/html/dpluso/" local="131297458760162586" remote="131297668200000000" Dst="1" />
<file name="ui-bg_flat_0_000000_40x100.png" server="192.168.1.2//var/www/html/dpluso/" local="131297458760102549" remote="131297668200000000" Dst="1" />
<file name="ui-bg_flat_0_ffffff_40x100.png" server="192.168.1.2//var/www/html/dpluso/" local="131297458760192609" remote="131297668200000000" Dst="1" />
<file name="ui-bg_flat_80_000000_40x100.png" server="192.168.1.2//var/www/html/dpluso/" local="131297458760222632" remote="131297668200000000" Dst="1" />
<file name="ui-bg_glass_30_87a71b_1x400.png" server="192.168.1.2//var/www/html/dpluso/" local="131297458760252649" remote="131297668200000000" Dst="1" />
<file name="ui-bg_glass_30_cdea6d_1x400.png" server="192.168.1.2//var/www/html/dpluso/" local="131297458760272662" remote="131297668200000000" Dst="1" />
<file name="ui-bg_glass_30_db1174_1x400.png" server="192.168.1.2//var/www/html/dpluso/" local="131297458760302685" remote="131297668200000000" Dst="1" />
<file name="ui-bg_glass_30_e4ebee_1x400.png" server="192.168.1.2//var/www/html/dpluso/" local="131297458760322696" remote="131297668200000000" Dst="1" />
<file name="ui-bg_inset-soft_95_fef1ec_1x100.png" server="192.168.1.2//var/www/html/dpluso/" local="131297458760372732" remote="131297668200000000" Dst="1" />
<file name="ui-bg_highlight-soft_30_d2e4ea_1x100.png" server="192.168.1.2//var/www/html/dpluso/" local="131297458760332702" remote="131297668200000000" Dst="1" />
<file name="ui-icons_222222_256x240.png" server="192.168.1.2//var/www/html/dpluso/" local="131297458760422762" remote="131297668200000000" Dst="1" />
<file name="ui-icons_2f4248_256x240.png" server="192.168.1.2//var/www/html/dpluso/" local="131297458760432775" remote="131297668200000000" Dst="1" />
<file name="ui-icons_cd0a0a_256x240.png" server="192.168.1.2//var/www/html/dpluso/" local="131297458760462789" remote="131297668200000000" Dst="1" />
<file name="ui-icons_ffffff_256x240.png" server="192.168.1.2//var/www/html/dpluso/" local="131297458760512826" remote="131297668200000000" Dst="1" />
</dwsync>